Users/gheine/.nova/nova.conf
gilt_nova-11.2.1.dist-info/DESCRIPTION.rst
gilt_nova-11.2.1.dist-info/METADATA
gilt_nova-11.2.1.dist-info/RECORD
gilt_nova-11.2.1.dist-info/WHEEL
gilt_nova-11.2.1.dist-info/entry_points.txt
gilt_nova-11.2.1.dist-info/metadata.json
gilt_nova-11.2.1.dist-info/namespace_packages.txt
gilt_nova-11.2.1.dist-info/top_level.txt
nova/__init__.py
nova/cli/__init__.py
nova/cli/bootstrap.py
nova/cli/main.py
nova/cli/controllers/__init__.py
nova/cli/controllers/base.py
nova/cli/controllers/deploy/__init__.py
nova/cli/controllers/deploy/deploy.py
nova/cli/controllers/setup/__init__.py
nova/cli/controllers/setup/setup.py
nova/cli/controllers/stack/__init__.py
nova/cli/controllers/stack/stack.py
nova/cli/controllers/stash/__init__.py
nova/cli/controllers/stash/stash.py
nova/cli/controllers/update/__init__.py
nova/cli/controllers/update/update.py
nova/cli/plugins/__init__.py
nova/core/__init__.py
nova/core/exc.py
nova/core/cfn_pyplates/__init__.py
nova/core/cfn_pyplates/core.py
nova/core/cfn_pyplates/exceptions.py
nova/core/cfn_pyplates/functions.py
nova/core/cfn_pyplates/options.py
nova/core/deploy/__init__.py
nova/core/deploy/deploy_stack.py
nova/core/managers/__init__.py
nova/core/managers/aws_manager.py
nova/core/managers/docker_manager.py
nova/core/managers/manager_provider.py
nova/core/managers/version_manager.py
nova/core/spec/__init__.py
nova/core/spec/custom_scripts.py
nova/core/spec/environment.py
nova/core/spec/nova_service_loader.py
nova/core/spec/nova_service_schema.yml
nova/core/spec/service.py
nova/core/spec/service_log_mapping.py
nova/core/spec/stack.py
nova/core/stack/__init__.py
nova/core/stack/create_stack.py
nova/core/stack/update_stack.py
nova/core/stash/__init__.py
nova/core/stash/decrypt.py
nova/core/stash/encrypt.py
nova/core/templates/__init__.py
nova/core/templates/deploy-scripts/cleanup_space.sh
nova/core/templates/deploy-scripts/common_functions.sh
nova/core/templates/deploy-scripts/deregister_from_elb.sh
nova/core/templates/deploy-scripts/kill_docker_container.sh
nova/core/templates/deploy-scripts/register_with_elb.sh
nova/core/templates/instance-scripts/configure-cloudwatch-logs-agent.py.txt
nova/core/templates/instance-scripts/nova-env-setup.sh
