Metadata-Version: 2.0
Name: gilt-nova
Version: 11.2.1
Summary: Collection of utilities to easily deploy services to AWS.
Home-page: https://github.com/gilt/nova
Author: Gilt Groupe
Author-email: gilt-nova-dev@googlegroups.com
License: MIT
Keywords: AWS CodeDeploy Cloudformation Deployment Gilt
Platform: UNKNOWN
Classifier: Development Status :: 5 - Production/Stable
Classifier: Environment :: Console
Classifier: Intended Audience :: Developers
Classifier: Intended Audience :: System Administrators
Classifier: Topic :: Software Development :: Build Tools
Classifier: License :: OSI Approved :: MIT License
Classifier: Operating System :: POSIX :: Linux
Classifier: Programming Language :: Python
Classifier: Programming Language :: Python :: 2.7
Classifier: Programming Language :: Python :: 3.4
Classifier: Programming Language :: Python :: 3.5
Classifier: Programming Language :: Python :: Implementation :: CPython
Requires-Dist: Cerberus
Requires-Dist: GitPython
Requires-Dist: Jinja2
Requires-Dist: argcomplete (==1.4.1)
Requires-Dist: boto3 (>=1.3.1)
Requires-Dist: cement (==2.8.2)
Requires-Dist: colorama
Requires-Dist: docker-py (>=1.8.0)
Requires-Dist: docopt
Requires-Dist: ordereddict
Requires-Dist: pyaml
Requires-Dist: pycrypto
Requires-Dist: six (>=1.10.0)
Requires-Dist: termcolor
